connectable/__init__.py
connectable/base.py
connectable-1.1.0.dist-info/top_level.txt
connectable-1.1.0.dist-info/METADATA
connectable-1.1.0.dist-info/DESCRIPTION.rst
connectable-1.1.0.dist-info/metadata.json
connectable-1.1.0.dist-info/WHEEL
connectable-1.1.0.dist-info/RECORD
