Metadata-Version: 2.0
Name: connectable
Version: 1.1.0
Summary: A simple, yet powerful, implementation of QTs signal / slots pattern for Python3
Home-page: https://github.com/timothycrosley/connectable
Author: Timothy Crosley
Author-email: timothy.crosley@gmail.com
License: MIT
Keywords: Python,Python3
Platform: UNKNOWN
Classifier: Development Status :: 6 - Mature
Classifier: Intended Audience :: Developers
Classifier: Natural Language :: English
Classifier: Environment :: Console
Classifier: License :: OSI Approved :: MIT License
Classifier: Programming Language :: Python
Classifier: Programming Language :: Python :: 3
Classifier: Programming Language :: Python :: 3.2
Classifier: Programming Language :: Python :: 3.3
Classifier: Programming Language :: Python :: 3.4
Classifier: Programming Language :: Python :: 3.5
Classifier: Topic :: Software Development :: Libraries
Classifier: Topic :: Utilities
